pytest_nengo.py
nengo/__init__.py
nengo/base.py
nengo/cache.py
nengo/config.py
nengo/connection.py
nengo/dists.py
nengo/ensemble.py
nengo/exceptions.py
nengo/learning_rules.py
nengo/network.py
nengo/neurons.py
nengo/node.py
nengo/params.py
nengo/presets.py
nengo/probe.py
nengo/processes.py
nengo/rc.py
nengo/simulator.py
nengo/solvers.py
nengo/synapses.py
nengo/transforms.py
nengo/version.py
nengo/_vendor/README.rst
nengo/_vendor/__init__.py
nengo/_vendor/requirements.txt
nengo/_vendor/portalocker/__about__.py
nengo/_vendor/portalocker/__init__.py
nengo/_vendor/portalocker/constants.py
nengo/_vendor/portalocker/exceptions.py
nengo/_vendor/portalocker/portalocker.py
nengo/_vendor/portalocker/utils.py
nengo/_vendor/scipy/__init__.py
nengo/_vendor/scipy/special.py
nengo/_vendor/scipy/sparse/README.md
nengo/_vendor/scipy/sparse/__init__.py
nengo/_vendor/scipy/sparse/linalg_expm.py
nengo/_vendor/scipy/sparse/linalg_interface.py
nengo/_vendor/scipy/sparse/linalg_onenormest.py
nengo/_vendor/scipy/sparse/sputils.py
nengo/builder/__init__.py
nengo/builder/builder.py
nengo/builder/connection.py
nengo/builder/ensemble.py
nengo/builder/learning_rules.py
nengo/builder/network.py
nengo/builder/neurons.py
nengo/builder/node.py
nengo/builder/operator.py
nengo/builder/optimizer.py
nengo/builder/probe.py
nengo/builder/processes.py
nengo/builder/signal.py
nengo/builder/transforms.py
nengo/builder/tests/__init__.py
nengo/builder/tests/test_builder.py
nengo/builder/tests/test_connection.py
nengo/builder/tests/test_learning_rules.py
nengo/builder/tests/test_neurons.py
nengo/builder/tests/test_node.py
nengo/builder/tests/test_operator.py
nengo/builder/tests/test_optimizer.py
nengo/builder/tests/test_probe.py
nengo/builder/tests/test_processes.py
nengo/builder/tests/test_signal.py
nengo/builder/tests/test_transforms.py
nengo/builder/tests/test_transforms_conv.py
nengo/data/__init__.py
nengo/data/betaincinv22_table.npz
nengo/networks/__init__.py
nengo/networks/actionselection.py
nengo-4.1.0.dist-info/licenses/LICENSE.rst
nengo-4.1.0.dist-info/METADATA
nengo-4.1.0.dist-info/WHEEL
nengo-4.1.0.dist-info/entry_points.txt
nengo-4.1.0.dist-info/top_level.txt
nengo-4.1.0.dist-info/RECORD
