Metadata-Version: 2.4
Name: nengo
Version: 4.1.0
Summary: Tools for building and simulating large-scale neural models
Home-page: https://www.nengo.ai/nengo
Author: Nengo Developers
Author-email: terry.stewart@gmail.com
License: GNU General Public License, version 2
Classifier: Development Status :: 5 - Production/Stable
Classifier: Framework :: Nengo
Classifier: Intended Audience :: Science/Research
Classifier: License :: OSI Approved :: GNU General Public License v2 (GPLv2)
Classifier: Operating System :: OS Independent
Classifier: Programming Language :: Python :: 3 :: Only
Classifier: Programming Language :: Python :: 3.6
Classifier: Programming Language :: Python :: 3.7
Classifier: Programming Language :: Python :: 3.8
Classifier: Programming Language :: Python :: 3.9
Classifier: Topic :: Scientific/Engineering :: Artificial Intelligence
Requires-Python: >=3.8
License-File: LICENSE.rst
Requires-Dist: numpy>=1.19
Provides-Extra: all
Requires-Dist: sphinx>=1.8; extra == "all"
Requires-Dist: jupyter; extra == "all"
Requires-Dist: matplotlib>=1.4; extra == "all"
Requires-Dist: nbsphinx; extra == "all"
Requires-Dist: numpydoc>=0.6; extra == "all"
Requires-Dist: nengo_sphinx_theme>=1.2.0; extra == "all"
Requires-Dist: scipy>=0.13; extra == "all"
Requires-Dist: scikit-learn; extra == "all"
Requires-Dist: jupyter; extra == "all"
Requires-Dist: matplotlib>=1.4; extra == "all"
Requires-Dist: pytest>=3.9.1; extra == "all"
Requires-Dist: pytest-allclose; extra == "all"
Requires-Dist: pytest-plt; extra == "all"
Requires-Dist: pytest-rng; extra == "all"
Provides-Extra: docs
Requires-Dist: sphinx>=1.8; extra == "docs"
Requires-Dist: jupyter; extra == "docs"
Requires-Dist: matplotlib>=1.4; extra == "docs"
Requires-Dist: nbsphinx; extra == "docs"
Requires-Dist: numpydoc>=0.6; extra == "docs"
Requires-Dist: nengo_sphinx_theme>=1.2.0; extra == "docs"
Provides-Extra: optional
Requires-Dist: scipy>=0.13; extra == "optional"
Requires-Dist: scikit-learn; extra == "optional"
Provides-Extra: tests
Requires-Dist: jupyter; extra == "tests"
Requires-Dist: matplotlib>=1.4; extra == "tests"
Requires-Dist: pytest>=3.9.1; extra == "tests"
Requires-Dist: pytest-allclose; extra == "tests"
Requires-Dist: pytest-plt; extra == "tests"
Requires-Dist: pytest-rng; extra == "tests"
Dynamic: author
Dynamic: author-email
Dynamic: classifier
Dynamic: description
Dynamic: home-page
Dynamic: license
Dynamic: license-file
Dynamic: provides-extra
Dynamic: requires-dist
Dynamic: requires-python
Dynamic: summary
